README.txt
setup.cfg
setup.py
pulling/Avro.py
pulling/Csv.py
pulling/Docx.py
pulling/Json.py
pulling/Pdf.py
pulling/Rtf.py
pulling/Txt.py
pulling/__init__.py
pulling.egg-info/PKG-INFO
pulling.egg-info/SOURCES.txt
pulling.egg-info/dependency_links.txt
pulling.egg-info/not-zip-safe
pulling.egg-info/top_level.txt