Metadata-Version: 1.0
Name: pulling
Version: 1.4.1
Summary: Pulling is an open source python repository for working with files of different extensions.
Home-page: https://github.com/ItYaS/pulling
Author: ItYaS
Author-email: ryaboshapkoseraph@gmail.com
License: Apache License 2.0
Platform: UNKNOWN
